blackrenderer/__init__.py
blackrenderer/__main__.py
blackrenderer/_version.py
blackrenderer/dumpCOLRv1Glyph.py
blackrenderer/font.py
blackrenderer/render.py
blackrenderer/backends/__init__.py
blackrenderer/backends/base.py
blackrenderer/backends/cairo.py
blackrenderer/backends/coregraphics.py
blackrenderer/backends/pathCollector.py
blackrenderer/backends/skia.py
blackrenderer/backends/svg.py
blackrenderer/backends/sweepGradient.py
blackrenderer-0.6.0.dist-info/LICENSE.txt
blackrenderer-0.6.0.dist-info/METADATA
blackrenderer-0.6.0.dist-info/WHEEL
blackrenderer-0.6.0.dist-info/entry_points.txt
blackrenderer-0.6.0.dist-info/top_level.txt
blackrenderer-0.6.0.dist-info/RECORD
