Metadata-Version: 2.1
Name: blackrenderer
Version: 0.6.0
Summary: A Python-based renderer for OpenType COLRv1 fonts, with multiple backends.
Home-page: https://github.com/BlackFoundryCom/black-renderer
Author: Black Foundry, Just van Rossum, Samuel Hornus
Author-email: justvanrossum@gmail.com
License: Apache Software License 2.0
Requires-Python: >=3.7
Provides-Extra: skia
Provides-Extra: cairo
Provides-Extra: cg
License-File: LICENSE.txt
